[
  {
    "id": "121301",
    "nama": "Panyabungan",
    "id_kab": "1213"
  },
  {
    "id": "121302",
    "nama": "Panyabungan Utara",
    "id_kab": "1213"
  },
  {
    "id": "121303",
    "nama": "Panyabungan Timur",
    "id_kab": "1213"
  },
  {
    "id": "121304",
    "nama": "Panyabungan Selatan",
    "id_kab": "1213"
  },
  {
    "id": "121305",
    "nama": "Panyabungan Barat",
    "id_kab": "1213"
  },
  {
    "id": "121306",
    "nama": "Siabu",
    "id_kab": "1213"
  },
  {
    "id": "121307",
    "nama": "Bukit Malintang",
    "id_kab": "1213"
  },
  {
    "id": "121308",
    "nama": "Kotanopan",
    "id_kab": "1213"
  },
  {
    "id": "121309",
    "nama": "Lembah Sorik Marapi",
    "id_kab": "1213"
  },
  {
    "id": "121310",
    "nama": "Tambangan",
    "id_kab": "1213"
  },
  {
    "id": "121311",
    "nama": "Ulu Pungkut",
    "id_kab": "1213"
  },
  {
    "id": "121312",
    "nama": "Muara Sipongi",
    "id_kab": "1213"
  },
  {
    "id": "121313",
    "nama": "Batang Natal",
    "id_kab": "1213"
  },
  {
    "id": "121314",
    "nama": "Lingga Bayu",
    "id_kab": "1213"
  },
  {
    "id": "121315",
    "nama": "Batahan",
    "id_kab": "1213"
  },
  {
    "id": "121316",
    "nama": "Natal",
    "id_kab": "1213"
  },
  {
    "id": "121317",
    "nama": "Muara Batang Gadis",
    "id_kab": "1213"
  },
  {
    "id": "121318",
    "nama": "Ranto Baek",
    "id_kab": "1213"
  },
  {
    "id": "121319",
    "nama": "Huta Bargot",
    "id_kab": "1213"
  },
  {
    "id": "121320",
    "nama": "Puncak Sorik Marapi",
    "id_kab": "1213"
  },
  {
    "id": "121321",
    "nama": "Pakantan",
    "id_kab": "1213"
  },
  {
    "id": "121322",
    "nama": "Sinunukan",
    "id_kab": "1213"
  },
  {
    "id": "121323",
    "nama": "Naga Juang",
    "id_kab": "1213"
  }
]