[
  {
    "id": "161301",
    "nama": "Rupit",
    "id_kab": "1613"
  },
  {
    "id": "161302",
    "nama": "Rawas Ulu",
    "id_kab": "1613"
  },
  {
    "id": "161303",
    "nama": "Nibung",
    "id_kab": "1613"
  },
  {
    "id": "161304",
    "nama": "Rawas Ilir",
    "id_kab": "1613"
  },
  {
    "id": "161305",
    "nama": "Karang Dapo",
    "id_kab": "1613"
  },
  {
    "id": "161306",
    "nama": "Karang Jaya",
    "id_kab": "1613"
  },
  {
    "id": "161307",
    "nama": "Ulu Rawas",
    "id_kab": "1613"
  }
]