[
  {
    "id": "180601",
    "nama": "Kota Agung (Kota Agung Pusat)",
    "id_kab": "1806"
  },
  {
    "id": "180602",
    "nama": "Talang Padang",
    "id_kab": "1806"
  },
  {
    "id": "180603",
    "nama": "Wonosobo",
    "id_kab": "1806"
  },
  {
    "id": "180604",
    "nama": "Pulau Panggung",
    "id_kab": "1806"
  },
  {
    "id": "180609",
    "nama": "Cukuh Balak",
    "id_kab": "1806"
  },
  {
    "id": "180611",
    "nama": "Pugung",
    "id_kab": "1806"
  },
  {
    "id": "180612",
    "nama": "Semaka",
    "id_kab": "1806"
  },
  {
    "id": "180613",
    "nama": "Sumberejo (Sumber Rejo)",
    "id_kab": "1806"
  },
  {
    "id": "180615",
    "nama": "Ulu Belu (Ulubelu)",
    "id_kab": "1806"
  },
  {
    "id": "180616",
    "nama": "Pematang Sawa",
    "id_kab": "1806"
  },
  {
    "id": "180617",
    "nama": "Kelumbayan (Klumbayan)",
    "id_kab": "1806"
  },
  {
    "id": "180618",
    "nama": "Kota Agung Barat",
    "id_kab": "1806"
  },
  {
    "id": "180619",
    "nama": "Kota Agung Timur",
    "id_kab": "1806"
  },
  {
    "id": "180620",
    "nama": "Gisting",
    "id_kab": "1806"
  },
  {
    "id": "180621",
    "nama": "Gunung Alip",
    "id_kab": "1806"
  },
  {
    "id": "180624",
    "nama": "Limau",
    "id_kab": "1806"
  },
  {
    "id": "180625",
    "nama": "Bandar Negeri Semuong",
    "id_kab": "1806"
  },
  {
    "id": "180626",
    "nama": "Air Naningan",
    "id_kab": "1806"
  },
  {
    "id": "180627",
    "nama": "Bulok",
    "id_kab": "1806"
  },
  {
    "id": "180628",
    "nama": "Kelumbayan Barat (Klumbayan Barat)",
    "id_kab": "1806"
  }
]