[
  {
    "id": "35.19.01",
    "nama": "Kebonsari (Kebon Sari)",
    "id_kab": "35.19"
  },
  {
    "id": "35.19.02",
    "nama": "Dolopo",
    "id_kab": "35.19"
  },
  {
    "id": "35.19.03",
    "nama": "Geger",
    "id_kab": "35.19"
  },
  {
    "id": "35.19.04",
    "nama": "Dagangan",
    "id_kab": "35.19"
  },
  {
    "id": "35.19.05",
    "nama": "Kare",
    "id_kab": "35.19"
  },
  {
    "id": "35.19.06",
    "nama": "Gemarang",
    "id_kab": "35.19"
  },
  {
    "id": "35.19.07",
    "nama": "Wungu",
    "id_kab": "35.19"
  },
  {
    "id": "35.19.08",
    "nama": "Madiun",
    "id_kab": "35.19"
  },
  {
    "id": "35.19.09",
    "nama": "Jiwan",
    "id_kab": "35.19"
  },
  {
    "id": "35.19.10",
    "nama": "Balerejo",
    "id_kab": "35.19"
  },
  {
    "id": "35.19.11",
    "nama": "Mejayan",
    "id_kab": "35.19"
  },
  {
    "id": "35.19.12",
    "nama": "Saradan",
    "id_kab": "35.19"
  },
  {
    "id": "35.19.13",
    "nama": "Pilangkenceng",
    "id_kab": "35.19"
  },
  {
    "id": "35.19.14",
    "nama": "Sawahan",
    "id_kab": "35.19"
  },
  {
    "id": "35.19.15",
    "nama": "Wonoasri",
    "id_kab": "35.19"
  }
]