[
  {
    "id": "52.05.01",
    "nama": "Dompu",
    "id_kab": "52.05"
  },
  {
    "id": "52.05.02",
    "nama": "Kempo",
    "id_kab": "52.05"
  },
  {
    "id": "52.05.03",
    "nama": "Hu'u",
    "id_kab": "52.05"
  },
  {
    "id": "52.05.04",
    "nama": "Kilo",
    "id_kab": "52.05"
  },
  {
    "id": "52.05.05",
    "nama": "Woja",
    "id_kab": "52.05"
  },
  {
    "id": "52.05.06",
    "nama": "Pekat",
    "id_kab": "52.05"
  },
  {
    "id": "52.05.07",
    "nama": "Manggalewa",
    "id_kab": "52.05"
  },
  {
    "id": "52.05.08",
    "nama": "Pajo",
    "id_kab": "52.05"
  }
]