[
  {
    "id": "73.07.01",
    "nama": "Sinjai Barat",
    "id_kab": "73.07"
  },
  {
    "id": "73.07.02",
    "nama": "Sinjai Selatan",
    "id_kab": "73.07"
  },
  {
    "id": "73.07.03",
    "nama": "Sinjai Timur",
    "id_kab": "73.07"
  },
  {
    "id": "73.07.04",
    "nama": "Sinjai Tengah",
    "id_kab": "73.07"
  },
  {
    "id": "73.07.05",
    "nama": "Sinjai Utara",
    "id_kab": "73.07"
  },
  {
    "id": "73.07.06",
    "nama": "Bulupoddo",
    "id_kab": "73.07"
  },
  {
    "id": "73.07.07",
    "nama": "Sinjai Borong",
    "id_kab": "73.07"
  },
  {
    "id": "73.07.08",
    "nama": "Tellu Limpoe",
    "id_kab": "73.07"
  },
  {
    "id": "73.07.09",
    "nama": "Pulau Sembilan",
    "id_kab": "73.07"
  }
]