[
  {
    "id": "930301",
    "nama": "Obaa",
    "id_kab": "9303"
  },
  {
    "id": "930302",
    "nama": "Mambioman Bapai",
    "id_kab": "9303"
  },
  {
    "id": "930303",
    "nama": "Citak-Mitak (Citakmitak)",
    "id_kab": "9303"
  },
  {
    "id": "930304",
    "nama": "Edera",
    "id_kab": "9303"
  },
  {
    "id": "930305",
    "nama": "Haju",
    "id_kab": "9303"
  },
  {
    "id": "930306",
    "nama": "Assue",
    "id_kab": "9303"
  },
  {
    "id": "930307",
    "nama": "Kaibar",
    "id_kab": "9303"
  },
  {
    "id": "930308",
    "nama": "Passue",
    "id_kab": "9303"
  },
  {
    "id": "930309",
    "nama": "Minyamur",
    "id_kab": "9303"
  },
  {
    "id": "930310",
    "nama": "Venaha",
    "id_kab": "9303"
  },
  {
    "id": "930311",
    "nama": "Syahcame",
    "id_kab": "9303"
  },
  {
    "id": "930312",
    "nama": "Yakomi",
    "id_kab": "9303"
  },
  {
    "id": "930313",
    "nama": "Bamgi",
    "id_kab": "9303"
  },
  {
    "id": "930314",
    "nama": "Passue Bawah",
    "id_kab": "9303"
  },
  {
    "id": "930315",
    "nama": "Ti Zain",
    "id_kab": "9303"
  }
]