[
  {
    "id": "1104212001",
    "nama": "Pantan Tengah",
    "id_kec": "110421"
  },
  {
    "id": "1104212002",
    "nama": "Rusip",
    "id_kec": "110421"
  },
  {
    "id": "1104212003",
    "nama": "Pilar",
    "id_kec": "110421"
  },
  {
    "id": "1104212004",
    "nama": "Arul Pertik",
    "id_kec": "110421"
  },
  {
    "id": "1104212005",
    "nama": "Pilar Jaya",
    "id_kec": "110421"
  },
  {
    "id": "1104212006",
    "nama": "Tirmi Ara",
    "id_kec": "110421"
  },
  {
    "id": "1104212007",
    "nama": "Atu Singkih",
    "id_kec": "110421"
  },
  {
    "id": "1104212008",
    "nama": "Pantan Bener",
    "id_kec": "110421"
  },
  {
    "id": "1104212009",
    "nama": "Kerawang",
    "id_kec": "110421"
  },
  {
    "id": "1104212010",
    "nama": "Mekar Maju",
    "id_kec": "110421"
  },
  {
    "id": "1104212011",
    "nama": "Paya Tampu/Tumpu",
    "id_kec": "110421"
  },
  {
    "id": "1104212012",
    "nama": "Tanjung",
    "id_kec": "110421"
  },
  {
    "id": "1104212013",
    "nama": "Meurandeh/Merandeh Paya",
    "id_kec": "110421"
  },
  {
    "id": "1104212014",
    "nama": "Kuala Rawa",
    "id_kec": "110421"
  },
  {
    "id": "1104212015",
    "nama": "Pilar Wih Kiri",
    "id_kec": "110421"
  },
  {
    "id": "1104212016",
    "nama": "Lut Jaya",
    "id_kec": "110421"
  }
]