[
  {
    "id": "1111012001",
    "nama": "Keude Aceh",
    "id_kec": "111101"
  },
  {
    "id": "1111012002",
    "nama": "Sangso",
    "id_kec": "111101"
  },
  {
    "id": "1111012003",
    "nama": "Pante Rheeng/Rheng",
    "id_kec": "111101"
  },
  {
    "id": "1111012004",
    "nama": "Meuliek",
    "id_kec": "111101"
  },
  {
    "id": "1111012005",
    "nama": "Namploh Baro",
    "id_kec": "111101"
  },
  {
    "id": "1111012006",
    "nama": "Namploh Manyang",
    "id_kec": "111101"
  },
  {
    "id": "1111012007",
    "nama": "Namploh Blang Garang",
    "id_kec": "111101"
  },
  {
    "id": "1111012008",
    "nama": "Namploh Krueng",
    "id_kec": "111101"
  },
  {
    "id": "1111012009",
    "nama": "Namploh Papeun (Namploh Papeuen)",
    "id_kec": "111101"
  },
  {
    "id": "1111012010",
    "nama": "Meunasah Lueng",
    "id_kec": "111101"
  },
  {
    "id": "1111012011",
    "nama": "Lhok Seumira",
    "id_kec": "111101"
  },
  {
    "id": "1111012012",
    "nama": "Ulee Jeumatan",
    "id_kec": "111101"
  },
  {
    "id": "1111012013",
    "nama": "Lancok",
    "id_kec": "111101"
  },
  {
    "id": "1111012014",
    "nama": "Paloh",
    "id_kec": "111101"
  },
  {
    "id": "1111012015",
    "nama": "Mesjid Baro",
    "id_kec": "111101"
  },
  {
    "id": "1111012016",
    "nama": "Batee Iliek",
    "id_kec": "111101"
  },
  {
    "id": "1111012017",
    "nama": "Pulo Baroh",
    "id_kec": "111101"
  },
  {
    "id": "1111012018",
    "nama": "Matang Wakeuh",
    "id_kec": "111101"
  },
  {
    "id": "1111012019",
    "nama": "Darussalam",
    "id_kec": "111101"
  },
  {
    "id": "1111012020",
    "nama": "Matang Jereung (Matang Jareung)",
    "id_kec": "111101"
  },
  {
    "id": "1111012021",
    "nama": "Matang",
    "id_kec": "111101"
  },
  {
    "id": "1111012022",
    "nama": "Cot Mane",
    "id_kec": "111101"
  },
  {
    "id": "1111012023",
    "nama": "Alue Barat",
    "id_kec": "111101"
  },
  {
    "id": "1111012024",
    "nama": "Cot Siren",
    "id_kec": "111101"
  },
  {
    "id": "1111012025",
    "nama": "Ulee Alue",
    "id_kec": "111101"
  },
  {
    "id": "1111012026",
    "nama": "Pineung Siribee (Pineung Siri Bee)",
    "id_kec": "111101"
  },
  {
    "id": "1111012027",
    "nama": "Gampong Baro",
    "id_kec": "111101"
  },
  {
    "id": "1111012028",
    "nama": "Kandang",
    "id_kec": "111101"
  },
  {
    "id": "1111012029",
    "nama": "Gampong Putoh",
    "id_kec": "111101"
  },
  {
    "id": "1111012030",
    "nama": "Mideun Jok",
    "id_kec": "111101"
  },
  {
    "id": "1111012031",
    "nama": "Mideun Geudong",
    "id_kec": "111101"
  },
  {
    "id": "1111012032",
    "nama": "Lueng Keubeu",
    "id_kec": "111101"
  },
  {
    "id": "1111012033",
    "nama": "Geulumpang/Glumpang Bungkok",
    "id_kec": "111101"
  },
  {
    "id": "1111012034",
    "nama": "Glumpang Meulum",
    "id_kec": "111101"
  },
  {
    "id": "1111012035",
    "nama": "Cot Meurak Baroh",
    "id_kec": "111101"
  },
  {
    "id": "1111012036",
    "nama": "Cot Meurak Blang",
    "id_kec": "111101"
  },
  {
    "id": "1111012037",
    "nama": "Meurah",
    "id_kec": "111101"
  },
  {
    "id": "1111012038",
    "nama": "Ulee Ue",
    "id_kec": "111101"
  },
  {
    "id": "1111012039",
    "nama": "Matang Teungoh",
    "id_kec": "111101"
  },
  {
    "id": "1111012040",
    "nama": "Tanjong Baro",
    "id_kec": "111101"
  },
  {
    "id": "1111012041",
    "nama": "Angkieng Barat (Ankieng Barat)",
    "id_kec": "111101"
  },
  {
    "id": "1111012042",
    "nama": "Meunasah Lincah",
    "id_kec": "111101"
  },
  {
    "id": "1111012043",
    "nama": "Meunasah Lancok",
    "id_kec": "111101"
  },
  {
    "id": "1111012044",
    "nama": "Meunasah Puuk",
    "id_kec": "111101"
  },
  {
    "id": "1111012045",
    "nama": "Tonjongan Idem (Tanjongan Idem)",
    "id_kec": "111101"
  },
  {
    "id": "1111012084",
    "nama": "Geulumpang/Glumpang Payong",
    "id_kec": "111101"
  }
]