[
  {
    "id": "1115082001",
    "nama": "Alue Bata",
    "id_kec": "111508"
  },
  {
    "id": "1115082002",
    "nama": "Gunong Sapek",
    "id_kec": "111508"
  },
  {
    "id": "1115082003",
    "nama": "Sarah Mantok",
    "id_kec": "111508"
  },
  {
    "id": "1115082004",
    "nama": "Pasie Luah (Pasi Luah)",
    "id_kec": "111508"
  },
  {
    "id": "1115082005",
    "nama": "Gunong Gulungo (Geulugo)",
    "id_kec": "111508"
  },
  {
    "id": "1115082006",
    "nama": "Gunong Kupok",
    "id_kec": "111508"
  },
  {
    "id": "1115082007",
    "nama": "Gunong Pungki (Gunong Pungkie)",
    "id_kec": "111508"
  },
  {
    "id": "1115082008",
    "nama": "Alue Siron",
    "id_kec": "111508"
  },
  {
    "id": "1115082009",
    "nama": "Cot Mue",
    "id_kec": "111508"
  },
  {
    "id": "1115082010",
    "nama": "Babah Rot",
    "id_kec": "111508"
  },
  {
    "id": "1115082011",
    "nama": "Babah Dua",
    "id_kec": "111508"
  },
  {
    "id": "1115082012",
    "nama": "Batu Raja",
    "id_kec": "111508"
  },
  {
    "id": "1115082013",
    "nama": "Simpang Jaya",
    "id_kec": "111508"
  },
  {
    "id": "1115082014",
    "nama": "Sumber Daya",
    "id_kec": "111508"
  },
  {
    "id": "1115082015",
    "nama": "Rantau Selamat",
    "id_kec": "111508"
  },
  {
    "id": "1115082016",
    "nama": "Alue Sepeng (Seupeung)",
    "id_kec": "111508"
  },
  {
    "id": "1115082017",
    "nama": "Krueng Itam",
    "id_kec": "111508"
  },
  {
    "id": "1115082018",
    "nama": "Alue Gajah",
    "id_kec": "111508"
  },
  {
    "id": "1115082019",
    "nama": "Alue Labu (Alue Labue)",
    "id_kec": "111508"
  },
  {
    "id": "1115082020",
    "nama": "Gapa Garu",
    "id_kec": "111508"
  },
  {
    "id": "1115082021",
    "nama": "Kuala Tadu",
    "id_kec": "111508"
  },
  {
    "id": "1115082022",
    "nama": "Cot Mee",
    "id_kec": "111508"
  }
]