[
  {
    "id": "1214042001",
    "nama": "Duru",
    "id_kec": "121404"
  },
  {
    "id": "1214042002",
    "nama": "Tuwaso",
    "id_kec": "121404"
  },
  {
    "id": "1214042003",
    "nama": "Hilioromao (Hilioro Mao)",
    "id_kec": "121404"
  },
  {
    "id": "1214042004",
    "nama": "Eho",
    "id_kec": "121404"
  },
  {
    "id": "1214042005",
    "nama": "Sialema",
    "id_kec": "121404"
  },
  {
    "id": "1214042006",
    "nama": "Bowonifaoso (Bawonifaoso)",
    "id_kec": "121404"
  },
  {
    "id": "1214042007",
    "nama": "Hilianombasela",
    "id_kec": "121404"
  },
  {
    "id": "1214042008",
    "nama": "Lumbui Melayu",
    "id_kec": "121404"
  },
  {
    "id": "1214042009",
    "nama": "Hiliorodua Tebolo (Hilioro Dua Tebolo)",
    "id_kec": "121404"
  },
  {
    "id": "1214042010",
    "nama": "Tebolo Melayu",
    "id_kec": "121404"
  },
  {
    "id": "1214042021",
    "nama": "Lumbui Nias",
    "id_kec": "121404"
  },
  {
    "id": "1214042022",
    "nama": "Baruyu Sibohou",
    "id_kec": "121404"
  },
  {
    "id": "1214042023",
    "nama": "Sepakat",
    "id_kec": "121404"
  },
  {
    "id": "1214042024",
    "nama": "Tano Mokinu",
    "id_kec": "121404"
  },
  {
    "id": "1214042025",
    "nama": "Hilikana",
    "id_kec": "121404"
  },
  {
    "id": "1214042026",
    "nama": "Hilinifaese",
    "id_kec": "121404"
  },
  {
    "id": "1214042027",
    "nama": "Omega",
    "id_kec": "121404"
  }
]