[
  {
    "id": "13.02.12.2001",
    "nama": "Sulit Air",
    "id_kec": "13.02.12"
  },
  {
    "id": "13.02.12.2002",
    "nama": "Tanjung Balik",
    "id_kec": "13.02.12"
  },
  {
    "id": "13.02.12.2003",
    "nama": "Paninjauan",
    "id_kec": "13.02.12"
  },
  {
    "id": "13.02.12.2004",
    "nama": "Kuncir",
    "id_kec": "13.02.12"
  },
  {
    "id": "13.02.12.2005",
    "nama": "Katialo",
    "id_kec": "13.02.12"
  },
  {
    "id": "13.02.12.2006",
    "nama": "Pasilihan",
    "id_kec": "13.02.12"
  },
  {
    "id": "13.02.12.2007",
    "nama": "Bukit Kanduang",
    "id_kec": "13.02.12"
  },
  {
    "id": "13.02.12.2008",
    "nama": "Sibarambang",
    "id_kec": "13.02.12"
  },
  {
    "id": "13.02.12.2009",
    "nama": "Labuh Panjang",
    "id_kec": "13.02.12"
  }
]