[
  {
    "id": "14.03.11.2001",
    "nama": "Tanjungmedang (Tanjung Medang)",
    "id_kec": "14.03.11"
  },
  {
    "id": "14.03.11.2002",
    "nama": "Telukrhu (Teluk Rhu)",
    "id_kec": "14.03.11"
  },
  {
    "id": "14.03.11.2003",
    "nama": "Tanjungpunak (Tanjung Punak)",
    "id_kec": "14.03.11"
  },
  {
    "id": "14.03.11.2004",
    "nama": "Kador",
    "id_kec": "14.03.11"
  },
  {
    "id": "14.03.11.2005",
    "nama": "Titi Akar",
    "id_kec": "14.03.11"
  },
  {
    "id": "14.03.11.2006",
    "nama": "Hutan Ayu",
    "id_kec": "14.03.11"
  },
  {
    "id": "14.03.11.2007",
    "nama": "Suka Damai",
    "id_kec": "14.03.11"
  },
  {
    "id": "14.03.11.2008",
    "nama": "Puteri Sembilan",
    "id_kec": "14.03.11"
  }
]