[
  {
    "id": "1406061001",
    "nama": "Kota Lama",
    "id_kec": "140606"
  },
  {
    "id": "1406062003",
    "nama": "Kota Intan",
    "id_kec": "140606"
  },
  {
    "id": "1406062004",
    "nama": "Muara Dilam",
    "id_kec": "140606"
  },
  {
    "id": "1406062008",
    "nama": "Kota Raya",
    "id_kec": "140606"
  },
  {
    "id": "1406062009",
    "nama": "Kota Baru",
    "id_kec": "140606"
  },
  {
    "id": "1406062010",
    "nama": "Sungai Kuti",
    "id_kec": "140606"
  },
  {
    "id": "1406062011",
    "nama": "Pasir Indah",
    "id_kec": "140606"
  },
  {
    "id": "1406062012",
    "nama": "Pasir Luhur",
    "id_kec": "140606"
  },
  {
    "id": "1406062017",
    "nama": "Bukit Intan Makmur",
    "id_kec": "140606"
  },
  {
    "id": "1406062018",
    "nama": "Bagan Tujuh",
    "id_kec": "140606"
  }
]