[
  {
    "id": "1604072001",
    "nama": "Bangke",
    "id_kec": "160407"
  },
  {
    "id": "1604072002",
    "nama": "Tebat Langsat",
    "id_kec": "160407"
  },
  {
    "id": "1604072003",
    "nama": "Singapure (Singapura)",
    "id_kec": "160407"
  },
  {
    "id": "1604072004",
    "nama": "Gunung Liwat (Gunung Lewat)",
    "id_kec": "160407"
  },
  {
    "id": "1604072005",
    "nama": "Kebun Jati (Kebon Jati)",
    "id_kec": "160407"
  },
  {
    "id": "1604072006",
    "nama": "Bintuhan",
    "id_kec": "160407"
  },
  {
    "id": "1604072007",
    "nama": "Mutar Alam Baru (Muntar Alam Baru)",
    "id_kec": "160407"
  },
  {
    "id": "1604072008",
    "nama": "Pandan Arang Ulu",
    "id_kec": "160407"
  },
  {
    "id": "1604072009",
    "nama": "Mutar Alam Lama (Muntar Alam Lama)",
    "id_kec": "160407"
  },
  {
    "id": "1604072010",
    "nama": "Tanjung Raman",
    "id_kec": "160407"
  },
  {
    "id": "1604072011",
    "nama": "Tunggul Bute",
    "id_kec": "160407"
  },
  {
    "id": "1604072012",
    "nama": "Karang Endah",
    "id_kec": "160407"
  },
  {
    "id": "1604072013",
    "nama": "Karang Agung",
    "id_kec": "160407"
  },
  {
    "id": "1604072014",
    "nama": "Suka Raja (Sukaraja)",
    "id_kec": "160407"
  },
  {
    "id": "1604072015",
    "nama": "Gedung Agung",
    "id_kec": "160407"
  },
  {
    "id": "1604072016",
    "nama": "Kota Agung",
    "id_kec": "160407"
  },
  {
    "id": "1604072017",
    "nama": "Lawang Agung",
    "id_kec": "160407"
  },
  {
    "id": "1604072018",
    "nama": "Sukarami (Sukarame)",
    "id_kec": "160407"
  },
  {
    "id": "1604072019",
    "nama": "Tanjung Beringin",
    "id_kec": "160407"
  },
  {
    "id": "1604072020",
    "nama": "Pagaruyung (Pagar Ruyung)",
    "id_kec": "160407"
  },
  {
    "id": "1604072031",
    "nama": "Muara Gula",
    "id_kec": "160407"
  },
  {
    "id": "1604072032",
    "nama": "Tanjung Bulan",
    "id_kec": "160407"
  }
]