[
  {
    "id": "1605212001",
    "nama": "Sukowarno",
    "id_kec": "160521"
  },
  {
    "id": "1605212002",
    "nama": "Sugih Waras",
    "id_kec": "160521"
  },
  {
    "id": "1605212003",
    "nama": "Bangun Rejo",
    "id_kec": "160521"
  },
  {
    "id": "1605212004",
    "nama": "Ciptodadi",
    "id_kec": "160521"
  },
  {
    "id": "1605212005",
    "nama": "Sukarena",
    "id_kec": "160521"
  },
  {
    "id": "1605212006",
    "nama": "Yudha Karya Bakti (Yudha Karya Bhakti)",
    "id_kec": "160521"
  },
  {
    "id": "1605212007",
    "nama": "Rantau Alih",
    "id_kec": "160521"
  },
  {
    "id": "1605212008",
    "nama": "Ciptodadi II",
    "id_kec": "160521"
  }
]