[
  {
    "id": "1708011007",
    "nama": "Keban Agung",
    "id_kec": "170801"
  },
  {
    "id": "1708012001",
    "nama": "Kota Agung",
    "id_kec": "170801"
  },
  {
    "id": "1708012002",
    "nama": "Kembang Seri",
    "id_kec": "170801"
  },
  {
    "id": "1708012003",
    "nama": "Pagar Agung",
    "id_kec": "170801"
  },
  {
    "id": "1708012004",
    "nama": "Embong Ijuk",
    "id_kec": "170801"
  },
  {
    "id": "1708012005",
    "nama": "Gunung Agung",
    "id_kec": "170801"
  },
  {
    "id": "1708012006",
    "nama": "Talang Pito",
    "id_kec": "170801"
  },
  {
    "id": "1708012008",
    "nama": "Cinto Mandi (Cinta Mandi)",
    "id_kec": "170801"
  },
  {
    "id": "1708012009",
    "nama": "Limbur Lama (Lembur Lama)",
    "id_kec": "170801"
  },
  {
    "id": "1708012010",
    "nama": "Taba Baru",
    "id_kec": "170801"
  },
  {
    "id": "1708012011",
    "nama": "Bukit Menyan",
    "id_kec": "170801"
  },
  {
    "id": "1708012016",
    "nama": "Batu Belarik",
    "id_kec": "170801"
  },
  {
    "id": "1708012017",
    "nama": "Embong Sido",
    "id_kec": "170801"
  },
  {
    "id": "1708012022",
    "nama": "Talang Sawah",
    "id_kec": "170801"
  },
  {
    "id": "1708012023",
    "nama": "Sosokan Cinta Mandi",
    "id_kec": "170801"
  },
  {
    "id": "1708012024",
    "nama": "Muara Langkap",
    "id_kec": "170801"
  },
  {
    "id": "1708012025",
    "nama": "Air Raman",
    "id_kec": "170801"
  },
  {
    "id": "1708012028",
    "nama": "Langgar Jaya",
    "id_kec": "170801"
  },
  {
    "id": "1708012029",
    "nama": "Cinta Mandi Baru",
    "id_kec": "170801"
  }
]