[
  {
    "id": "32.04.26.2001",
    "nama": "Nagreg",
    "id_kec": "32.04.26"
  },
  {
    "id": "32.04.26.2002",
    "nama": "Bojong",
    "id_kec": "32.04.26"
  },
  {
    "id": "32.04.26.2003",
    "nama": "Ciaro",
    "id_kec": "32.04.26"
  },
  {
    "id": "32.04.26.2004",
    "nama": "Ciherang",
    "id_kec": "32.04.26"
  },
  {
    "id": "32.04.26.2005",
    "nama": "Citaman",
    "id_kec": "32.04.26"
  },
  {
    "id": "32.04.26.2006",
    "nama": "Mandalawangi",
    "id_kec": "32.04.26"
  },
  {
    "id": "32.04.26.2007",
    "nama": "Nagreg Kendan",
    "id_kec": "32.04.26"
  },
  {
    "id": "32.04.26.2008",
    "nama": "Ganjar Sabar",
    "id_kec": "32.04.26"
  }
]