[
  {
    "id": "3201042001",
    "nama": "Gununggeulis (Gunung Geulis)",
    "id_kec": "320104"
  },
  {
    "id": "3201042002",
    "nama": "Cilebut Timur",
    "id_kec": "320104"
  },
  {
    "id": "3201042003",
    "nama": "Cilebut Barat",
    "id_kec": "320104"
  },
  {
    "id": "3201042004",
    "nama": "Cibanon",
    "id_kec": "320104"
  },
  {
    "id": "3201042005",
    "nama": "Nagrak",
    "id_kec": "320104"
  },
  {
    "id": "3201042006",
    "nama": "Sukatani",
    "id_kec": "320104"
  },
  {
    "id": "3201042007",
    "nama": "Sukaraja",
    "id_kec": "320104"
  },
  {
    "id": "3201042008",
    "nama": "Cikeas",
    "id_kec": "320104"
  },
  {
    "id": "3201042009",
    "nama": "Pasir Jambu",
    "id_kec": "320104"
  },
  {
    "id": "3201042010",
    "nama": "Cimandala",
    "id_kec": "320104"
  },
  {
    "id": "3201042011",
    "nama": "Cijujung",
    "id_kec": "320104"
  },
  {
    "id": "3201042012",
    "nama": "Cadasngampar (Cadas Ngampar)",
    "id_kec": "320104"
  },
  {
    "id": "3201042013",
    "nama": "Pasirlaja",
    "id_kec": "320104"
  }
]