[
  {
    "id": "3201312001",
    "nama": "Sukamantri",
    "id_kec": "320131"
  },
  {
    "id": "3201312002",
    "nama": "Sirnagalih",
    "id_kec": "320131"
  },
  {
    "id": "3201312003",
    "nama": "Pasireurih",
    "id_kec": "320131"
  },
  {
    "id": "3201312004",
    "nama": "Tamansari",
    "id_kec": "320131"
  },
  {
    "id": "3201312005",
    "nama": "Sukaluyu",
    "id_kec": "320131"
  },
  {
    "id": "3201312006",
    "nama": "Sukaresmi",
    "id_kec": "320131"
  },
  {
    "id": "3201312007",
    "nama": "Sukajaya",
    "id_kec": "320131"
  },
  {
    "id": "3201312008",
    "nama": "Sukajadi",
    "id_kec": "320131"
  }
]