[
  {
    "id": "3207102001",
    "nama": "Panawangan",
    "id_kec": "320710"
  },
  {
    "id": "3207102002",
    "nama": "Sagalaherang",
    "id_kec": "320710"
  },
  {
    "id": "3207102003",
    "nama": "Nagarapageuh",
    "id_kec": "320710"
  },
  {
    "id": "3207102004",
    "nama": "Nagarajati",
    "id_kec": "320710"
  },
  {
    "id": "3207102005",
    "nama": "Nagarajaya",
    "id_kec": "320710"
  },
  {
    "id": "3207102006",
    "nama": "Kertayasa",
    "id_kec": "320710"
  },
  {
    "id": "3207102007",
    "nama": "Indragiri",
    "id_kec": "320710"
  },
  {
    "id": "3207102008",
    "nama": "Cinyasag",
    "id_kec": "320710"
  },
  {
    "id": "3207102009",
    "nama": "Sadapaingan",
    "id_kec": "320710"
  },
  {
    "id": "3207102010",
    "nama": "Jagabaya",
    "id_kec": "320710"
  },
  {
    "id": "3207102011",
    "nama": "Gardujaya",
    "id_kec": "320710"
  },
  {
    "id": "3207102012",
    "nama": "Karangpaningal",
    "id_kec": "320710"
  },
  {
    "id": "3207102013",
    "nama": "Bangunjaya",
    "id_kec": "320710"
  },
  {
    "id": "3207102014",
    "nama": "Girilaya",
    "id_kec": "320710"
  },
  {
    "id": "3207102015",
    "nama": "Kertajaya",
    "id_kec": "320710"
  },
  {
    "id": "3207102016",
    "nama": "Nagarawangi",
    "id_kec": "320710"
  },
  {
    "id": "3207102017",
    "nama": "Mekarbuana",
    "id_kec": "320710"
  },
  {
    "id": "3207102018",
    "nama": "Natanegara",
    "id_kec": "320710"
  }
]