[
  {
    "id": "3214122001",
    "nama": "Cilangkap",
    "id_kec": "321412"
  },
  {
    "id": "3214122002",
    "nama": "Cicadas",
    "id_kec": "321412"
  },
  {
    "id": "3214122003",
    "nama": "Hegarmanah",
    "id_kec": "321412"
  },
  {
    "id": "3214122004",
    "nama": "Babakancikao",
    "id_kec": "321412"
  },
  {
    "id": "3214122005",
    "nama": "Kadumekar",
    "id_kec": "321412"
  },
  {
    "id": "3214122006",
    "nama": "Marancang (Maracang)",
    "id_kec": "321412"
  },
  {
    "id": "3214122007",
    "nama": "Ciwareng",
    "id_kec": "321412"
  },
  {
    "id": "3214122008",
    "nama": "Mulyamekar",
    "id_kec": "321412"
  },
  {
    "id": "3214122009",
    "nama": "Cigelam",
    "id_kec": "321412"
  }
]