[
  {
    "id": "33.22.16.2001",
    "nama": "Bancak",
    "id_kec": "33.22.16"
  },
  {
    "id": "33.22.16.2002",
    "nama": "Wonokerto",
    "id_kec": "33.22.16"
  },
  {
    "id": "33.22.16.2003",
    "nama": "Jlumpang",
    "id_kec": "33.22.16"
  },
  {
    "id": "33.22.16.2004",
    "nama": "Bantal",
    "id_kec": "33.22.16"
  },
  {
    "id": "33.22.16.2005",
    "nama": "Rejosari",
    "id_kec": "33.22.16"
  },
  {
    "id": "33.22.16.2006",
    "nama": "Plumutan",
    "id_kec": "33.22.16"
  },
  {
    "id": "33.22.16.2007",
    "nama": "Lembu",
    "id_kec": "33.22.16"
  },
  {
    "id": "33.22.16.2008",
    "nama": "Pucung",
    "id_kec": "33.22.16"
  },
  {
    "id": "33.22.16.2009",
    "nama": "Boto",
    "id_kec": "33.22.16"
  }
]