[
  {
    "id": "3307011007",
    "nama": "Wadaslintang (Wadas Lintang)",
    "id_kec": "330701"
  },
  {
    "id": "3307012001",
    "nama": "Kaligowong",
    "id_kec": "330701"
  },
  {
    "id": "3307012002",
    "nama": "Sumbersari",
    "id_kec": "330701"
  },
  {
    "id": "3307012003",
    "nama": "Sumberejo",
    "id_kec": "330701"
  },
  {
    "id": "3307012004",
    "nama": "Erorejo",
    "id_kec": "330701"
  },
  {
    "id": "3307012005",
    "nama": "Karanganyar (Karang Anyar)",
    "id_kec": "330701"
  },
  {
    "id": "3307012006",
    "nama": "Panerusan",
    "id_kec": "330701"
  },
  {
    "id": "3307012008",
    "nama": "Plunjaran",
    "id_kec": "330701"
  },
  {
    "id": "3307012009",
    "nama": "Kumejing",
    "id_kec": "330701"
  },
  {
    "id": "3307012010",
    "nama": "Lancar",
    "id_kec": "330701"
  },
  {
    "id": "3307012011",
    "nama": "Somogede",
    "id_kec": "330701"
  },
  {
    "id": "3307012012",
    "nama": "Trimulyo",
    "id_kec": "330701"
  },
  {
    "id": "3307012013",
    "nama": "Tirip",
    "id_kec": "330701"
  },
  {
    "id": "3307012014",
    "nama": "Besuki",
    "id_kec": "330701"
  },
  {
    "id": "3307012015",
    "nama": "Gumelar",
    "id_kec": "330701"
  },
  {
    "id": "3307012016",
    "nama": "Ngalian",
    "id_kec": "330701"
  },
  {
    "id": "3307012017",
    "nama": "Kalidadap",
    "id_kec": "330701"
  }
]