[
  {
    "id": "3312242001",
    "nama": "Songbledeg",
    "id_kec": "331224"
  },
  {
    "id": "3312242002",
    "nama": "Ketos",
    "id_kec": "331224"
  },
  {
    "id": "3312242003",
    "nama": "Paranggupito",
    "id_kec": "331224"
  },
  {
    "id": "3312242004",
    "nama": "Gudangharjo",
    "id_kec": "331224"
  },
  {
    "id": "3312242005",
    "nama": "Gunturharjo",
    "id_kec": "331224"
  },
  {
    "id": "3312242006",
    "nama": "Sambiharjo",
    "id_kec": "331224"
  },
  {
    "id": "3312242007",
    "nama": "Johunut",
    "id_kec": "331224"
  },
  {
    "id": "3312242008",
    "nama": "Gendayakan",
    "id_kec": "331224"
  }
]