[
  {
    "id": "3312081003",
    "nama": "Puloharjo",
    "id_kec": "331208"
  },
  {
    "id": "3312081009",
    "nama": "Ngadirejo",
    "id_kec": "331208"
  },
  {
    "id": "3312082001",
    "nama": "Basuhan",
    "id_kec": "331208"
  },
  {
    "id": "3312082002",
    "nama": "Pucung",
    "id_kec": "331208"
  },
  {
    "id": "3312082004",
    "nama": "Sindukarto (Sindukarta)",
    "id_kec": "331208"
  },
  {
    "id": "3312082005",
    "nama": "Panekan",
    "id_kec": "331208"
  },
  {
    "id": "3312082006",
    "nama": "Baleharjo",
    "id_kec": "331208"
  },
  {
    "id": "3312082007",
    "nama": "Sumberharjo",
    "id_kec": "331208"
  },
  {
    "id": "3312082008",
    "nama": "Minggarharjo",
    "id_kec": "331208"
  },
  {
    "id": "3312082010",
    "nama": "Tegalharjo",
    "id_kec": "331208"
  },
  {
    "id": "3312082011",
    "nama": "Eromoko",
    "id_kec": "331208"
  },
  {
    "id": "3312082012",
    "nama": "Ngunggahan",
    "id_kec": "331208"
  },
  {
    "id": "3312082013",
    "nama": "Tempurharjo",
    "id_kec": "331208"
  },
  {
    "id": "3312082014",
    "nama": "Pasekan",
    "id_kec": "331208"
  },
  {
    "id": "3312082015",
    "nama": "Ngandong",
    "id_kec": "331208"
  }
]