[
  {
    "id": "3316152001",
    "nama": "Gombang",
    "id_kec": "331615"
  },
  {
    "id": "3316152002",
    "nama": "Sarirejo",
    "id_kec": "331615"
  },
  {
    "id": "3316152003",
    "nama": "Karanganyar",
    "id_kec": "331615"
  },
  {
    "id": "3316152004",
    "nama": "Karang",
    "id_kec": "331615"
  },
  {
    "id": "3316152005",
    "nama": "Prantaan",
    "id_kec": "331615"
  },
  {
    "id": "3316152006",
    "nama": "Jeruk",
    "id_kec": "331615"
  },
  {
    "id": "3316152007",
    "nama": "Bogorejo",
    "id_kec": "331615"
  },
  {
    "id": "3316152008",
    "nama": "Gembol",
    "id_kec": "331615"
  },
  {
    "id": "3316152009",
    "nama": "Tempurejo",
    "id_kec": "331615"
  },
  {
    "id": "3316152010",
    "nama": "Gayam",
    "id_kec": "331615"
  },
  {
    "id": "3316152011",
    "nama": "Sendangrejo",
    "id_kec": "331615"
  },
  {
    "id": "3316152012",
    "nama": "Gandu",
    "id_kec": "331615"
  },
  {
    "id": "3316152013",
    "nama": "Nglengkir",
    "id_kec": "331615"
  },
  {
    "id": "3316152014",
    "nama": "Jurangjero",
    "id_kec": "331615"
  }
]