[
  {
    "id": "3326032001",
    "nama": "Tembelangunung (Tembelang Gunung)",
    "id_kec": "332603"
  },
  {
    "id": "3326032002",
    "nama": "Pamutuh",
    "id_kec": "332603"
  },
  {
    "id": "3326032003",
    "nama": "Depok",
    "id_kec": "332603"
  },
  {
    "id": "3326032004",
    "nama": "Wonosido",
    "id_kec": "332603"
  },
  {
    "id": "3326032005",
    "nama": "Timbangsari",
    "id_kec": "332603"
  },
  {
    "id": "3326032006",
    "nama": "Sidomulyo",
    "id_kec": "332603"
  },
  {
    "id": "3326032007",
    "nama": "Kutorembet",
    "id_kec": "332603"
  },
  {
    "id": "3326032008",
    "nama": "Lebakbarang",
    "id_kec": "332603"
  },
  {
    "id": "3326032009",
    "nama": "Kapundutan",
    "id_kec": "332603"
  },
  {
    "id": "3326032010",
    "nama": "Bantarkulon (Bantar Kulon)",
    "id_kec": "332603"
  },
  {
    "id": "3326032011",
    "nama": "Mendolo",
    "id_kec": "332603"
  }
]