[
  {
    "id": "3404142001",
    "nama": "Banyurejo (Banyu Rejo)",
    "id_kec": "340414"
  },
  {
    "id": "3404142002",
    "nama": "Tambakrejo (Tambak Rejo)",
    "id_kec": "340414"
  },
  {
    "id": "3404142003",
    "nama": "Sumberrejo (Sumber Rejo)",
    "id_kec": "340414"
  },
  {
    "id": "3404142004",
    "nama": "Pondokrejo (Pondok Rejo)",
    "id_kec": "340414"
  },
  {
    "id": "3404142005",
    "nama": "Mororejo (Moro Rejo)",
    "id_kec": "340414"
  },
  {
    "id": "3404142006",
    "nama": "Margorejo (Margo Rejo)",
    "id_kec": "340414"
  },
  {
    "id": "3404142007",
    "nama": "Lumbungrejo (Lumbung Rejo)",
    "id_kec": "340414"
  },
  {
    "id": "3404142008",
    "nama": "Merdikorejo (Merdiko Rejo)",
    "id_kec": "340414"
  }
]