[
  {
    "id": "3504162001",
    "nama": "Ngentrong",
    "id_kec": "350416"
  },
  {
    "id": "3504162002",
    "nama": "Gedangan",
    "id_kec": "350416"
  },
  {
    "id": "3504162003",
    "nama": "Sawo",
    "id_kec": "350416"
  },
  {
    "id": "3504162004",
    "nama": "Gamping",
    "id_kec": "350416"
  },
  {
    "id": "3504162005",
    "nama": "Campurdarat",
    "id_kec": "350416"
  },
  {
    "id": "3504162006",
    "nama": "Wates",
    "id_kec": "350416"
  },
  {
    "id": "3504162007",
    "nama": "Pelem",
    "id_kec": "350416"
  },
  {
    "id": "3504162008",
    "nama": "Pojok",
    "id_kec": "350416"
  },
  {
    "id": "3504162009",
    "nama": "Tanggung",
    "id_kec": "350416"
  }
]