[
  {
    "id": "3505062001",
    "nama": "Dadaplangu",
    "id_kec": "350506"
  },
  {
    "id": "3505062002",
    "nama": "Langon",
    "id_kec": "350506"
  },
  {
    "id": "3505062003",
    "nama": "Gembongan",
    "id_kec": "350506"
  },
  {
    "id": "3505062004",
    "nama": "Ringinanyar",
    "id_kec": "350506"
  },
  {
    "id": "3505062005",
    "nama": "Kebonduren",
    "id_kec": "350506"
  },
  {
    "id": "3505062006",
    "nama": "Bacem",
    "id_kec": "350506"
  },
  {
    "id": "3505062007",
    "nama": "Ponggok",
    "id_kec": "350506"
  },
  {
    "id": "3505062008",
    "nama": "Pojok",
    "id_kec": "350506"
  },
  {
    "id": "3505062009",
    "nama": "Kawedusan",
    "id_kec": "350506"
  },
  {
    "id": "3505062010",
    "nama": "Jatilengger",
    "id_kec": "350506"
  },
  {
    "id": "3505062011",
    "nama": "Bendo",
    "id_kec": "350506"
  },
  {
    "id": "3505062012",
    "nama": "Sidorejo",
    "id_kec": "350506"
  },
  {
    "id": "3505062013",
    "nama": "Maliran",
    "id_kec": "350506"
  },
  {
    "id": "3505062014",
    "nama": "Candirejo",
    "id_kec": "350506"
  },
  {
    "id": "3505062015",
    "nama": "Karangbendo",
    "id_kec": "350506"
  }
]