[
  {
    "id": "3508162001",
    "nama": "Pandansari",
    "id_kec": "350816"
  },
  {
    "id": "3508162002",
    "nama": "Krasak",
    "id_kec": "350816"
  },
  {
    "id": "3508162003",
    "nama": "Kedungjajang",
    "id_kec": "350816"
  },
  {
    "id": "3508162004",
    "nama": "Wonorejo",
    "id_kec": "350816"
  },
  {
    "id": "3508162005",
    "nama": "Umbul",
    "id_kec": "350816"
  },
  {
    "id": "3508162006",
    "nama": "Curahpetung",
    "id_kec": "350816"
  },
  {
    "id": "3508162007",
    "nama": "Grobogan",
    "id_kec": "350816"
  },
  {
    "id": "3508162008",
    "nama": "Bence",
    "id_kec": "350816"
  },
  {
    "id": "3508162009",
    "nama": "Jatisari",
    "id_kec": "350816"
  },
  {
    "id": "3508162010",
    "nama": "Tempursari",
    "id_kec": "350816"
  },
  {
    "id": "3508162011",
    "nama": "Bandaran",
    "id_kec": "350816"
  },
  {
    "id": "3508162012",
    "nama": "Sawaran Kulon",
    "id_kec": "350816"
  }
]