[
  {
    "id": "5102062001",
    "nama": "Bengkel",
    "id_kec": "510206"
  },
  {
    "id": "5102062002",
    "nama": "Pangkung Tibah",
    "id_kec": "510206"
  },
  {
    "id": "5102062003",
    "nama": "Belalang",
    "id_kec": "510206"
  },
  {
    "id": "5102062004",
    "nama": "Beraban",
    "id_kec": "510206"
  },
  {
    "id": "5102062005",
    "nama": "Buwit",
    "id_kec": "510206"
  },
  {
    "id": "5102062006",
    "nama": "Cepaka",
    "id_kec": "510206"
  },
  {
    "id": "5102062007",
    "nama": "Kaba-Kaba",
    "id_kec": "510206"
  },
  {
    "id": "5102062008",
    "nama": "Nyambu",
    "id_kec": "510206"
  },
  {
    "id": "5102062009",
    "nama": "Pandak Bandung",
    "id_kec": "510206"
  },
  {
    "id": "5102062010",
    "nama": "Pandak Gede",
    "id_kec": "510206"
  },
  {
    "id": "5102062011",
    "nama": "Nyitdah",
    "id_kec": "510206"
  },
  {
    "id": "5102062012",
    "nama": "Pejaten",
    "id_kec": "510206"
  },
  {
    "id": "5102062013",
    "nama": "Kediri",
    "id_kec": "510206"
  },
  {
    "id": "5102062014",
    "nama": "Abian Tuwung",
    "id_kec": "510206"
  },
  {
    "id": "5102062015",
    "nama": "Banjar Anyar",
    "id_kec": "510206"
  }
]