[
  {
    "id": "5171031005",
    "nama": "Dauh Puri",
    "id_kec": "517103"
  },
  {
    "id": "5171031007",
    "nama": "Pemecutan",
    "id_kec": "517103"
  },
  {
    "id": "5171031010",
    "nama": "Padangsambian",
    "id_kec": "517103"
  },
  {
    "id": "5171032001",
    "nama": "Padangsambian Klod/Kelod",
    "id_kec": "517103"
  },
  {
    "id": "5171032002",
    "nama": "Pemecutan Klod/Kelod",
    "id_kec": "517103"
  },
  {
    "id": "5171032003",
    "nama": "Dauh Puri Kauh",
    "id_kec": "517103"
  },
  {
    "id": "5171032004",
    "nama": "Dauh Puri Klod/Kelod",
    "id_kec": "517103"
  },
  {
    "id": "5171032006",
    "nama": "Dauh Puri Kangin",
    "id_kec": "517103"
  },
  {
    "id": "5171032008",
    "nama": "Tegal Harum",
    "id_kec": "517103"
  },
  {
    "id": "5171032009",
    "nama": "Tegal Kertha",
    "id_kec": "517103"
  },
  {
    "id": "5171032011",
    "nama": "Padang Sambian Kaja (Padangsambian Kaja)",
    "id_kec": "517103"
  }
]