[
  {
    "id": "5201132001",
    "nama": "Lembar",
    "id_kec": "520113"
  },
  {
    "id": "5201132002",
    "nama": "Jembatan Kembar",
    "id_kec": "520113"
  },
  {
    "id": "5201132003",
    "nama": "Mareje",
    "id_kec": "520113"
  },
  {
    "id": "5201132004",
    "nama": "Sekotong Timur",
    "id_kec": "520113"
  },
  {
    "id": "5201132005",
    "nama": "Labuan Tereng",
    "id_kec": "520113"
  },
  {
    "id": "5201132006",
    "nama": "Jembatan Gantung",
    "id_kec": "520113"
  },
  {
    "id": "5201132007",
    "nama": "Lembar Selatan",
    "id_kec": "520113"
  },
  {
    "id": "5201132008",
    "nama": "Mareje Timur",
    "id_kec": "520113"
  },
  {
    "id": "5201132009",
    "nama": "Jembatan Kembar Timur",
    "id_kec": "520113"
  },
  {
    "id": "5201132010",
    "nama": "Eyat Mayang",
    "id_kec": "520113"
  }
]