[
  {
    "id": "53.07.18.2001",
    "nama": "Rubit",
    "id_kec": "53.07.18"
  },
  {
    "id": "53.07.18.2002",
    "nama": "Wolomapa",
    "id_kec": "53.07.18"
  },
  {
    "id": "53.07.18.2003",
    "nama": "Baomekot",
    "id_kec": "53.07.18"
  },
  {
    "id": "53.07.18.2004",
    "nama": "Kajowair",
    "id_kec": "53.07.18"
  },
  {
    "id": "53.07.18.2005",
    "nama": "Hewokloang",
    "id_kec": "53.07.18"
  },
  {
    "id": "53.07.18.2006",
    "nama": "Heopuat",
    "id_kec": "53.07.18"
  },
  {
    "id": "53.07.18.2007",
    "nama": "Munerana",
    "id_kec": "53.07.18"
  }
]