[
  {
    "id": "5310152001",
    "nama": "Bangka Lelak",
    "id_kec": "531015"
  },
  {
    "id": "5310152002",
    "nama": "Gelong",
    "id_kec": "531015"
  },
  {
    "id": "5310152003",
    "nama": "Urang",
    "id_kec": "531015"
  },
  {
    "id": "5310152004",
    "nama": "Ketang",
    "id_kec": "531015"
  },
  {
    "id": "5310152005",
    "nama": "Pong Umpu (Pong Ompu)",
    "id_kec": "531015"
  },
  {
    "id": "5310152006",
    "nama": "Bangka Dese",
    "id_kec": "531015"
  },
  {
    "id": "5310152007",
    "nama": "Nati",
    "id_kec": "531015"
  },
  {
    "id": "5310152008",
    "nama": "Ndiwar",
    "id_kec": "531015"
  },
  {
    "id": "5310152009",
    "nama": "Bangka Tonggur",
    "id_kec": "531015"
  },
  {
    "id": "5310152010",
    "nama": "Lentang",
    "id_kec": "531015"
  }
]