[
  {
    "id": "5317052001",
    "nama": "Konda Maloba",
    "id_kec": "531705"
  },
  {
    "id": "5317052002",
    "nama": "Tana Modu",
    "id_kec": "531705"
  },
  {
    "id": "5317052003",
    "nama": "Malinjak",
    "id_kec": "531705"
  },
  {
    "id": "5317052004",
    "nama": "Wailawa",
    "id_kec": "531705"
  },
  {
    "id": "5317052005",
    "nama": "Dameka",
    "id_kec": "531705"
  },
  {
    "id": "5317052006",
    "nama": "Waimanu",
    "id_kec": "531705"
  },
  {
    "id": "5317052007",
    "nama": "Manurara",
    "id_kec": "531705"
  },
  {
    "id": "5317052008",
    "nama": "Elu",
    "id_kec": "531705"
  },
  {
    "id": "5317052009",
    "nama": "Oka Wacu",
    "id_kec": "531705"
  }
]