[
  {
    "id": "5320042001",
    "nama": "Raerobo",
    "id_kec": "532004"
  },
  {
    "id": "5320042002",
    "nama": "Mehona",
    "id_kec": "532004"
  },
  {
    "id": "5320042003",
    "nama": "Waduwalla (Waduwala)",
    "id_kec": "532004"
  },
  {
    "id": "5320042004",
    "nama": "Ledeke",
    "id_kec": "532004"
  },
  {
    "id": "5320042005",
    "nama": "Eilogo",
    "id_kec": "532004"
  },
  {
    "id": "5320042006",
    "nama": "Deme",
    "id_kec": "532004"
  },
  {
    "id": "5320042007",
    "nama": "Kotahawu",
    "id_kec": "532004"
  },
  {
    "id": "5320042008",
    "nama": "Dainao",
    "id_kec": "532004"
  },
  {
    "id": "5320042009",
    "nama": "Eikare",
    "id_kec": "532004"
  },
  {
    "id": "5320042010",
    "nama": "Loborui (Loboroi)",
    "id_kec": "532004"
  },
  {
    "id": "5320042011",
    "nama": "Halla Paji (Halapadji)",
    "id_kec": "532004"
  },
  {
    "id": "5320042012",
    "nama": "Ledetalo (Lede Talo)",
    "id_kec": "532004"
  }
]