[
  {
    "id": "61.02.06.2001",
    "nama": "Toho Hilir (Toho Ilir)",
    "id_kec": "61.02.06"
  },
  {
    "id": "61.02.06.2002",
    "nama": "Pak Laheng",
    "id_kec": "61.02.06"
  },
  {
    "id": "61.02.06.2003",
    "nama": "Kecurit",
    "id_kec": "61.02.06"
  },
  {
    "id": "61.02.06.2004",
    "nama": "Terap",
    "id_kec": "61.02.06"
  },
  {
    "id": "61.02.06.2005",
    "nama": "Sepang",
    "id_kec": "61.02.06"
  },
  {
    "id": "61.02.06.2006",
    "nama": "Pak Utan (Pakutan)",
    "id_kec": "61.02.06"
  },
  {
    "id": "61.02.06.2007",
    "nama": "Benuang",
    "id_kec": "61.02.06"
  },
  {
    "id": "61.02.06.2008",
    "nama": "Sambora (Sembora / Samboro)",
    "id_kec": "61.02.06"
  }
]