[
  {
    "id": "62.71.04.1001",
    "nama": "Bereng Bengkel",
    "id_kec": "62.71.04"
  },
  {
    "id": "62.71.04.1002",
    "nama": "Kalampangan",
    "id_kec": "62.71.04"
  },
  {
    "id": "62.71.04.1003",
    "nama": "Kereng Bangkirai",
    "id_kec": "62.71.04"
  },
  {
    "id": "62.71.04.1004",
    "nama": "Kameloh Baru",
    "id_kec": "62.71.04"
  },
  {
    "id": "62.71.04.1005",
    "nama": "Danau Tundai",
    "id_kec": "62.71.04"
  },
  {
    "id": "62.71.04.1006",
    "nama": "Sabaru",
    "id_kec": "62.71.04"
  }
]