[
  {
    "id": "6210081008",
    "nama": "Tumbang Marikoi",
    "id_kec": "621008"
  },
  {
    "id": "6210082001",
    "nama": "Lawang Kanji",
    "id_kec": "621008"
  },
  {
    "id": "6210082002",
    "nama": "Tumbang Mahuroi",
    "id_kec": "621008"
  },
  {
    "id": "6210082003",
    "nama": "Karetau Rambangun",
    "id_kec": "621008"
  },
  {
    "id": "6210082004",
    "nama": "Karetau Sarian",
    "id_kec": "621008"
  },
  {
    "id": "6210082005",
    "nama": "Tumbang Posu",
    "id_kec": "621008"
  },
  {
    "id": "6210082006",
    "nama": "Tumbang Maraya",
    "id_kec": "621008"
  },
  {
    "id": "6210082007",
    "nama": "Tumbang Anoi",
    "id_kec": "621008"
  }
]