[
  {
    "id": "6211012001",
    "nama": "Dandang",
    "id_kec": "621101"
  },
  {
    "id": "6211012002",
    "nama": "Talio",
    "id_kec": "621101"
  },
  {
    "id": "6211012003",
    "nama": "Pangkoh Hilir",
    "id_kec": "621101"
  },
  {
    "id": "6211012004",
    "nama": "Pangkoh Hulu",
    "id_kec": "621101"
  },
  {
    "id": "6211012005",
    "nama": "Kantan Muara",
    "id_kec": "621101"
  },
  {
    "id": "6211012006",
    "nama": "Talio Muara",
    "id_kec": "621101"
  },
  {
    "id": "6211012007",
    "nama": "Talio Hulu",
    "id_kec": "621101"
  },
  {
    "id": "6211012008",
    "nama": "Pangkoh Sari",
    "id_kec": "621101"
  },
  {
    "id": "6211012009",
    "nama": "Sanggang",
    "id_kec": "621101"
  },
  {
    "id": "6211012010",
    "nama": "Pantik",
    "id_kec": "621101"
  },
  {
    "id": "6211012011",
    "nama": "Belanti Siam",
    "id_kec": "621101"
  },
  {
    "id": "6211012012",
    "nama": "Gadabung",
    "id_kec": "621101"
  },
  {
    "id": "6211012013",
    "nama": "Mulyasari (Mulia Sari)",
    "id_kec": "621101"
  },
  {
    "id": "6211012014",
    "nama": "Kantan Dalam",
    "id_kec": "621101"
  },
  {
    "id": "6211012015",
    "nama": "Kantan Atas",
    "id_kec": "621101"
  },
  {
    "id": "6211012016",
    "nama": "Karya Bersama",
    "id_kec": "621101"
  }
]