[
  {
    "id": "63.02.10.2001",
    "nama": "Sungai Hanyar",
    "id_kec": "63.02.10"
  },
  {
    "id": "63.02.10.2002",
    "nama": "Sungai Seluang",
    "id_kec": "63.02.10"
  },
  {
    "id": "63.02.10.2003",
    "nama": "Pudi",
    "id_kec": "63.02.10"
  },
  {
    "id": "63.02.10.2004",
    "nama": "Mangga",
    "id_kec": "63.02.10"
  },
  {
    "id": "63.02.10.2005",
    "nama": "Wilas",
    "id_kec": "63.02.10"
  },
  {
    "id": "63.02.10.2006",
    "nama": "Pudi Seberang",
    "id_kec": "63.02.10"
  },
  {
    "id": "63.02.10.2007",
    "nama": "Sulangkit",
    "id_kec": "63.02.10"
  }
]