[
  {
    "id": "6301022001",
    "nama": "Sabuhur",
    "id_kec": "630102"
  },
  {
    "id": "6301022002",
    "nama": "Jorong",
    "id_kec": "630102"
  },
  {
    "id": "6301022003",
    "nama": "Asam Asam",
    "id_kec": "630102"
  },
  {
    "id": "6301022004",
    "nama": "Batalang",
    "id_kec": "630102"
  },
  {
    "id": "6301022005",
    "nama": "Swarangan",
    "id_kec": "630102"
  },
  {
    "id": "6301022006",
    "nama": "Muara Asam Asam",
    "id_kec": "630102"
  },
  {
    "id": "6301022007",
    "nama": "Alur",
    "id_kec": "630102"
  },
  {
    "id": "6301022008",
    "nama": "Asri Mulya (Asri Mulia)",
    "id_kec": "630102"
  },
  {
    "id": "6301022009",
    "nama": "Karang Rejo",
    "id_kec": "630102"
  },
  {
    "id": "6301022010",
    "nama": "Asam Jaya",
    "id_kec": "630102"
  },
  {
    "id": "6301022011",
    "nama": "Simpang Empat Sungai Baru (Sungaibaru)",
    "id_kec": "630102"
  }
]