[
  {
    "id": "6303021001",
    "nama": "Kertak Hanyar I",
    "id_kec": "630302"
  },
  {
    "id": "6303021008",
    "nama": "Manarap Lama",
    "id_kec": "630302"
  },
  {
    "id": "6303021015",
    "nama": "Mandarsari (Mandar Sari)",
    "id_kec": "630302"
  },
  {
    "id": "6303022005",
    "nama": "Pemangkih Laut (Pemangkih Baru)",
    "id_kec": "630302"
  },
  {
    "id": "6303022006",
    "nama": "Simpang Empat",
    "id_kec": "630302"
  },
  {
    "id": "6303022007",
    "nama": "Sei/Sungai Lakum",
    "id_kec": "630302"
  },
  {
    "id": "6303022009",
    "nama": "Manarap Baru",
    "id_kec": "630302"
  },
  {
    "id": "6303022010",
    "nama": "Kertak Hanyar II (Kertakhanyar II)",
    "id_kec": "630302"
  },
  {
    "id": "6303022014",
    "nama": "Pasar Kamis (Pasar Kemis)",
    "id_kec": "630302"
  },
  {
    "id": "6303022016",
    "nama": "Manarap Tengah",
    "id_kec": "630302"
  },
  {
    "id": "6303022017",
    "nama": "Belayung Baru",
    "id_kec": "630302"
  },
  {
    "id": "6303022021",
    "nama": "Benua Hanyar (Banua Hanyar)",
    "id_kec": "630302"
  },
  {
    "id": "6303022022",
    "nama": "Mekar Raya",
    "id_kec": "630302"
  }
]