[
  {
    "id": "6307061001",
    "nama": "Barabai Darat",
    "id_kec": "630706"
  },
  {
    "id": "6307061002",
    "nama": "Barabai Timur",
    "id_kec": "630706"
  },
  {
    "id": "6307061003",
    "nama": "Barabai Selatan",
    "id_kec": "630706"
  },
  {
    "id": "6307061004",
    "nama": "Barabai Utara",
    "id_kec": "630706"
  },
  {
    "id": "6307061005",
    "nama": "Barabai Barat",
    "id_kec": "630706"
  },
  {
    "id": "6307061006",
    "nama": "Bukat",
    "id_kec": "630706"
  },
  {
    "id": "6307062007",
    "nama": "Gambah",
    "id_kec": "630706"
  },
  {
    "id": "6307062008",
    "nama": "Kayu Bawang",
    "id_kec": "630706"
  },
  {
    "id": "6307062009",
    "nama": "Benawa Tengah",
    "id_kec": "630706"
  },
  {
    "id": "6307062010",
    "nama": "Mandingin",
    "id_kec": "630706"
  },
  {
    "id": "6307062011",
    "nama": "Pajukungan",
    "id_kec": "630706"
  },
  {
    "id": "6307062012",
    "nama": "Banua Budi",
    "id_kec": "630706"
  },
  {
    "id": "6307062013",
    "nama": "Banua Binjai",
    "id_kec": "630706"
  },
  {
    "id": "6307062014",
    "nama": "Banua Jingah",
    "id_kec": "630706"
  },
  {
    "id": "6307062015",
    "nama": "Ayuang",
    "id_kec": "630706"
  },
  {
    "id": "6307062016",
    "nama": "Babai",
    "id_kec": "630706"
  },
  {
    "id": "6307062017",
    "nama": "Awang Besar",
    "id_kec": "630706"
  },
  {
    "id": "6307062018",
    "nama": "Bakapas",
    "id_kec": "630706"
  }
]