[
  {
    "id": "64.72.02.1001",
    "nama": "Sungai Keledang",
    "id_kec": "64.72.02"
  },
  {
    "id": "64.72.02.1002",
    "nama": "Baqa",
    "id_kec": "64.72.02"
  },
  {
    "id": "64.72.02.1003",
    "nama": "Mesjid",
    "id_kec": "64.72.02"
  },
  {
    "id": "64.72.02.1009",
    "nama": "Mangkupalas",
    "id_kec": "64.72.02"
  },
  {
    "id": "64.72.02.1010",
    "nama": "Tenun Samarinda",
    "id_kec": "64.72.02"
  },
  {
    "id": "64.72.02.1011",
    "nama": "Gunung Panjang",
    "id_kec": "64.72.02"
  }
]