[
  {
    "id": "72.03.25.2001",
    "nama": "Sikara Tobata",
    "id_kec": "72.03.25"
  },
  {
    "id": "72.03.25.2002",
    "nama": "Alindau",
    "id_kec": "72.03.25"
  },
  {
    "id": "72.03.25.2003",
    "nama": "Oti",
    "id_kec": "72.03.25"
  },
  {
    "id": "72.03.25.2004",
    "nama": "Tamarenja",
    "id_kec": "72.03.25"
  },
  {
    "id": "72.03.25.2005",
    "nama": "Sipeso",
    "id_kec": "72.03.25"
  },
  {
    "id": "72.03.25.2006",
    "nama": "Sindosa",
    "id_kec": "72.03.25"
  }
]