[
  {
    "id": "7210122001",
    "nama": "Tulo",
    "id_kec": "721012"
  },
  {
    "id": "7210122002",
    "nama": "Langleso (Langaleso)",
    "id_kec": "721012"
  },
  {
    "id": "7210122003",
    "nama": "Watubula",
    "id_kec": "721012"
  },
  {
    "id": "7210122004",
    "nama": "Soulowe",
    "id_kec": "721012"
  },
  {
    "id": "7210122005",
    "nama": "Karawana",
    "id_kec": "721012"
  },
  {
    "id": "7210122006",
    "nama": "Kotapulu (Kota Pulu)",
    "id_kec": "721012"
  },
  {
    "id": "7210122007",
    "nama": "Kotarindau",
    "id_kec": "721012"
  },
  {
    "id": "7210122008",
    "nama": "Panturabate (Waturalele)",
    "id_kec": "721012"
  },
  {
    "id": "7210122009",
    "nama": "Maku",
    "id_kec": "721012"
  },
  {
    "id": "7210122010",
    "nama": "Potoya",
    "id_kec": "721012"
  },
  {
    "id": "7210122011",
    "nama": "Kabobona",
    "id_kec": "721012"
  }
]