[
  {
    "id": "73.01.11.2001",
    "nama": "Buki",
    "id_kec": "73.01.11"
  },
  {
    "id": "73.01.11.2002",
    "nama": "Lalang Bata",
    "id_kec": "73.01.11"
  },
  {
    "id": "73.01.11.2003",
    "nama": "Balang Butung",
    "id_kec": "73.01.11"
  },
  {
    "id": "73.01.11.2004",
    "nama": "Kohala",
    "id_kec": "73.01.11"
  },
  {
    "id": "73.01.11.2005",
    "nama": "Bontolempangan",
    "id_kec": "73.01.11"
  },
  {
    "id": "73.01.11.2006",
    "nama": "Mekar Indah",
    "id_kec": "73.01.11"
  },
  {
    "id": "73.01.11.2007",
    "nama": "Buki Timur",
    "id_kec": "73.01.11"
  }
]