[
  {
    "id": "7408072001",
    "nama": "Walasiho",
    "id_kec": "740807"
  },
  {
    "id": "7408072002",
    "nama": "Wawo",
    "id_kec": "740807"
  },
  {
    "id": "7408072003",
    "nama": "Tinukari",
    "id_kec": "740807"
  },
  {
    "id": "7408072004",
    "nama": "Pumbolo",
    "id_kec": "740807"
  },
  {
    "id": "7408072005",
    "nama": "Ulu Wawo",
    "id_kec": "740807"
  },
  {
    "id": "7408072006",
    "nama": "Latawe",
    "id_kec": "740807"
  },
  {
    "id": "7408072007",
    "nama": "Salurengko",
    "id_kec": "740807"
  }
]