[
  {
    "id": "7503082001",
    "nama": "Huangobotu",
    "id_kec": "750308"
  },
  {
    "id": "7503082002",
    "nama": "Molotabu (Molutabu)",
    "id_kec": "750308"
  },
  {
    "id": "7503082003",
    "nama": "Oluhuta",
    "id_kec": "750308"
  },
  {
    "id": "7503082004",
    "nama": "Olele",
    "id_kec": "750308"
  },
  {
    "id": "7503082005",
    "nama": "Botutonuo (Botutonua)",
    "id_kec": "750308"
  },
  {
    "id": "7503082006",
    "nama": "Modelomo",
    "id_kec": "750308"
  },
  {
    "id": "7503082007",
    "nama": "Biluango",
    "id_kec": "750308"
  },
  {
    "id": "7503082008",
    "nama": "Botubarani",
    "id_kec": "750308"
  },
  {
    "id": "7503082009",
    "nama": "Bintalahe",
    "id_kec": "750308"
  }
]