[
  {
    "id": "7504132001",
    "nama": "Dudewulo",
    "id_kec": "750413"
  },
  {
    "id": "7504132002",
    "nama": "Tunas Jaya",
    "id_kec": "750413"
  },
  {
    "id": "7504132003",
    "nama": "Padengo",
    "id_kec": "750413"
  },
  {
    "id": "7504132004",
    "nama": "Molosifat (Molosipat)",
    "id_kec": "750413"
  },
  {
    "id": "7504132005",
    "nama": "Butungale",
    "id_kec": "750413"
  },
  {
    "id": "7504132006",
    "nama": "Persatuan",
    "id_kec": "750413"
  },
  {
    "id": "7504132007",
    "nama": "Molosifat Utara (Molosipat Utara)",
    "id_kec": "750413"
  }
]