[
  {
    "id": "7603082002",
    "nama": "Orobua",
    "id_kec": "760308"
  },
  {
    "id": "7603082003",
    "nama": "Paladan",
    "id_kec": "760308"
  },
  {
    "id": "7603082004",
    "nama": "Orobua Timur",
    "id_kec": "760308"
  },
  {
    "id": "7603082006",
    "nama": "Rante Puang",
    "id_kec": "760308"
  },
  {
    "id": "7603082007",
    "nama": "Satenetean",
    "id_kec": "760308"
  },
  {
    "id": "7603082008",
    "nama": "Lisuan Ada",
    "id_kec": "760308"
  },
  {
    "id": "7603082010",
    "nama": "Orobua Selatan",
    "id_kec": "760308"
  },
  {
    "id": "7603082012",
    "nama": "Malangkena Padang",
    "id_kec": "760308"
  },
  {
    "id": "7603082013",
    "nama": "Malimbong",
    "id_kec": "760308"
  },
  {
    "id": "7603082014",
    "nama": "Marampan Orobua",
    "id_kec": "760308"
  }
]