[
  {
    "id": "93.04.02.2001",
    "nama": "Atsj",
    "id_kec": "93.04.02"
  },
  {
    "id": "93.04.02.2002",
    "nama": "Sogoni",
    "id_kec": "93.04.02"
  },
  {
    "id": "93.04.02.2003",
    "nama": "Amanamkai",
    "id_kec": "93.04.02"
  },
  {
    "id": "93.04.02.2004",
    "nama": "Ambisu",
    "id_kec": "93.04.02"
  },
  {
    "id": "93.04.02.2005",
    "nama": "Bine",
    "id_kec": "93.04.02"
  },
  {
    "id": "93.04.02.2006",
    "nama": "Bipim",
    "id_kec": "93.04.02"
  },
  {
    "id": "93.04.02.2007",
    "nama": "Yasiuw",
    "id_kec": "93.04.02"
  },
  {
    "id": "93.04.02.2008",
    "nama": "Bakasai",
    "id_kec": "93.04.02"
  },
  {
    "id": "93.04.02.2009",
    "nama": "Cewewyamew",
    "id_kec": "93.04.02"
  }
]