[
  {
    "id": "9403132001",
    "nama": "Pugo",
    "id_kec": "940313"
  },
  {
    "id": "9403132002",
    "nama": "Waidide",
    "id_kec": "940313"
  },
  {
    "id": "9403132003",
    "nama": "Kopaidagi",
    "id_kec": "940313"
  },
  {
    "id": "9403132004",
    "nama": "Uwibutu",
    "id_kec": "940313"
  },
  {
    "id": "9403132005",
    "nama": "Tipago",
    "id_kec": "940313"
  },
  {
    "id": "9403132006",
    "nama": "Boba",
    "id_kec": "940313"
  },
  {
    "id": "9403132007",
    "nama": "Iyaidagi",
    "id_kec": "940313"
  },
  {
    "id": "9403132008",
    "nama": "Iyaitadi",
    "id_kec": "940313"
  },
  {
    "id": "9403132009",
    "nama": "Waiepo",
    "id_kec": "940313"
  }
]