[
  {
    "id": "9403242001",
    "nama": "Yabomaida",
    "id_kec": "940324"
  },
  {
    "id": "9403242002",
    "nama": "Akoubaida",
    "id_kec": "940324"
  },
  {
    "id": "9403242003",
    "nama": "Dauwagu",
    "id_kec": "940324"
  },
  {
    "id": "9403242004",
    "nama": "Ganeyetaka",
    "id_kec": "940324"
  },
  {
    "id": "9403242005",
    "nama": "Yabomaida II",
    "id_kec": "940324"
  },
  {
    "id": "9403242006",
    "nama": "Bodatadi",
    "id_kec": "940324"
  },
  {
    "id": "9403242007",
    "nama": "Ibouwagu",
    "id_kec": "940324"
  }
]