[
  {
    "id": "9504222001",
    "nama": "Bolubur",
    "id_kec": "950422"
  },
  {
    "id": "9504222002",
    "nama": "Geneluk",
    "id_kec": "950422"
  },
  {
    "id": "9504222003",
    "nama": "Tirib",
    "id_kec": "950422"
  },
  {
    "id": "9504222004",
    "nama": "Beremo",
    "id_kec": "950422"
  },
  {
    "id": "9504222005",
    "nama": "Pirage",
    "id_kec": "950422"
  },
  {
    "id": "9504222006",
    "nama": "Koinggambu",
    "id_kec": "950422"
  },
  {
    "id": "9504222007",
    "nama": "Liwina",
    "id_kec": "950422"
  },
  {
    "id": "9504222008",
    "nama": "Eragani",
    "id_kec": "950422"
  },
  {
    "id": "9504222009",
    "nama": "Luki",
    "id_kec": "950422"
  },
  {
    "id": "9504222011",
    "nama": "Tioner",
    "id_kec": "950422"
  },
  {
    "id": "9504222013",
    "nama": "Logulo",
    "id_kec": "950422"
  },
  {
    "id": "9504222014",
    "nama": "Bawi",
    "id_kec": "950422"
  }
]