[
  {
    "id": "9601071001",
    "nama": "Aimas",
    "id_kec": "960107"
  },
  {
    "id": "9601071002",
    "nama": "Malawili",
    "id_kec": "960107"
  },
  {
    "id": "9601071003",
    "nama": "Malawele",
    "id_kec": "960107"
  },
  {
    "id": "9601071006",
    "nama": "Mariat Pantai",
    "id_kec": "960107"
  },
  {
    "id": "9601071026",
    "nama": "Mariat Gunung",
    "id_kec": "960107"
  },
  {
    "id": "9601071029",
    "nama": "Warmon",
    "id_kec": "960107"
  },
  {
    "id": "9601071030",
    "nama": "Klabinain",
    "id_kec": "960107"
  },
  {
    "id": "9601071031",
    "nama": "Malasom",
    "id_kec": "960107"
  },
  {
    "id": "9601071032",
    "nama": "Klaigit",
    "id_kec": "960107"
  },
  {
    "id": "9601071034",
    "nama": "Malagusa",
    "id_kec": "960107"
  },
  {
    "id": "9601071035",
    "nama": "Klafma",
    "id_kec": "960107"
  },
  {
    "id": "9601072028",
    "nama": "Maibo",
    "id_kec": "960107"
  },
  {
    "id": "9601072033",
    "nama": "Aimo",
    "id_kec": "960107"
  },
  {
    "id": "9601072038",
    "nama": "Malasaum",
    "id_kec": "960107"
  }
]