[
  {
    "id": "9601062001",
    "nama": "Seget",
    "id_kec": "960106"
  },
  {
    "id": "9601062004",
    "nama": "Malabam (Malaban)",
    "id_kec": "960106"
  },
  {
    "id": "9601062005",
    "nama": "Pulau Kasim",
    "id_kec": "960106"
  },
  {
    "id": "9601062010",
    "nama": "Kasimle",
    "id_kec": "960106"
  },
  {
    "id": "9601062011",
    "nama": "Wewenagu",
    "id_kec": "960106"
  },
  {
    "id": "9601062012",
    "nama": "Wasingsan",
    "id_kec": "960106"
  },
  {
    "id": "9601062013",
    "nama": "Klayas",
    "id_kec": "960106"
  },
  {
    "id": "9601062014",
    "nama": "Wayenkede",
    "id_kec": "960106"
  },
  {
    "id": "9601062015",
    "nama": "Mobi",
    "id_kec": "960106"
  }
]